{"_id": "news::kstade::f47981d5bba8bb614d6ce7f5fbfcead54228b01e", "importDate": "2017-06-10T14:58:12+00:00", "item": {"link": "http://www.ksta.de/koeln/porz/gesamtschule-in-porz-raeume-fuer-inklusionsangebote-sollen-abgeschafft-werden-27754438", "topline": "Gesamtschule in Porz", "pubDate": "2017-06-10T14:51:07+00:00", "images": [{"credits": "Bild: dpa", "medium": "http://www.ksta.de/image/27756424/4x3/1024/768/c19496766d8a662051d49030aa1ec858/qE/inklusion.jpg", "large": "http://www.ksta.de/image/27756424/4x3/1024/768/c19496766d8a662051d49030aa1ec858/qE/inklusion.jpg", "small": "http://www.ksta.de/image/27756424/4x3/1024/768/c19496766d8a662051d49030aa1ec858/qE/inklusion.jpg", "description": "Symbolbild"}], "metadata": {"words": 367, "categories": [{"score": 1, "type": "XMN-CATEGORY", "uri": "http://meta.xminutes.net/xmn/cat::8ad645bd3ab11c6b968974fb99d999745f1102f9", "label": "education", "id": "cat::8ad645bd3ab11c6b968974fb99d999745f1102f9", "source": "dandelion"}, {"score": 0.538216376557703, "type": "XMN-CATEGORY", "uri": "http://meta.xminutes.net/xmn/cat::ee36d2e530c9887dc07a3ce41e2b3a67eb789e43", "label": "science", "id": "cat::ee36d2e530c9887dc07a3ce41e2b3a67eb789e43", "source": "dandelion"}, {"score": 0.4448490131603681, "type": "XMN-CATEGORY", "uri": "http://meta.xminutes.net/xmn/cat::30d5b344f498e127c4fe95baaf07ec11b463df1a", "label": "labour", "id": "cat::30d5b344f498e127c4fe95baaf07ec11b463df1a", "source": "dandelion"}, {"score": 0.333381738822897, "type": "XMN-CATEGORY", "uri": "http://meta.xminutes.net/xmn/cat::5879037e4dfcde65da53795915c6209e013a3e5e", "label": "arts", "id": "cat::5879037e4dfcde65da53795915c6209e013a3e5e", "source": "dandelion"}, {"score": 0.25061472719521927, "type": "XMN-CATEGORY", "uri": "http://meta.xminutes.net/xmn/cat::7cd8df3bc24e6e7b471bfdbcdce6e37f3ef904b9", "label": "lifestyle", "id": "cat::7cd8df3bc24e6e7b471bfdbcdce6e37f3ef904b9", "source": "dandelion"}, {"score": 0.22390631053393195, "type": "XMN-CATEGORY", "uri": "http://meta.xminutes.net/xmn/cat::e5026641ea6c3454d8323e4bcda7c99e1ea27157", "label": "sport", "id": "cat::e5026641ea6c3454d8323e4bcda7c99e1ea27157", "source": "dandelion"}, {"score": 0.21905424405091506, "type": "XMN-CATEGORY", "uri": "http://meta.xminutes.net/xmn/cat::8293fd2214e4290b6cf10422293efd7c62a266fb", "label": "economy", "id": "cat::8293fd2214e4290b6cf10422293efd7c62a266fb", "source": "dandelion"}, {"score": 0.20640596239208772, "type": "XMN-CATEGORY", "uri": "http://meta.xminutes.net/xmn/cat::5e76511a37f2b3772546b60817978efc2049bda4", "label": "politics", "id": "cat::5e76511a37f2b3772546b60817978efc2049bda4", "source": "dandelion"}, {"score": 0.16521348674651112, "type": "XMN-CATEGORY", "uri": "http://meta.xminutes.net/xmn/cat::4d650a7ffd73245d9b7581b655d895c46be679e9", "label": "health", "id": "cat::4d650a7ffd73245d9b7581b655d895c46be679e9", "source": "dandelion"}, {"score": 0.16272594007220215, "type": "XMN-CATEGORY", "uri": "http://meta.xminutes.net/xmn/cat::3e15dfb6e9f12776d1c01f2f02b61c46deab0d37", "label": "law", "id": "cat::3e15dfb6e9f12776d1c01f2f02b61c46deab0d37", "source": "dandelion"}], "authors": [], "sources": [{"type": "XMN-SOURCE", "uri": "http://meta.xminutes.net/xmn/ent::ec7fd3608340e87e1d14f611352cca7d2f83bac9", "label": "ksta.de", "id": "ent::ec7fd3608340e87e1d14f611352cca7d2f83bac9"}], "location": {"item": [], "url": [{"scope": "local", "resolved": [{"bounds": {"northeast": {"lng": 7.1618738, "lat": 50.929241}, "southwest": {"lng": 6.9735419, "lat": 50.826323}}, "location": {"long": 7.071989899999999, "lat": 50.87135900000001}, "formatted_address": "Porz, Cologne, Germany"}], "name": "porz"}], "entities": []}, "entities": [{"type": "CONCEPT", "uri": "https://www.wikidata.org/wiki/Q1055771", "label": "Inklusive Pädagogik", "score": 0.577019504432025, "surface": "Inklusionsangebote"}, {"type": "CONCEPT", "uri": "https://www.wikidata.org/wiki/Q331483", "label": "Abriss", "score": 0.36677284303345536, "surface": "Rückbau"}, {"type": "CONCEPT", "uri": "https://www.wikidata.org/wiki/Q646754", "label": "offener Brief", "score": 0.9790926399989435, "surface": "offenen Brief"}, {"type": "CONCEPT", "uri": "https://www.wikidata.org/wiki/Q1334101", "label": "Elternvertretung", "score": 0.4412468220828647, "surface": "Schulpflegschaft"}, {"type": "CONCEPT", "uri": "https://www.wikidata.org/wiki/Q331483", "label": "Abriss", "score": 0.36677284303345536, "surface": "Rückbau"}, {"type": "CONCEPT", "uri": "https://www.wikidata.org/wiki/Q682697", "label": "Gesamtschule", "score": 0.4417084042288585, "surface": "Gesamtschule"}, {"type": "CONCEPT", "uri": "https://www.wikidata.org/wiki/Q1055771", "label": "Inklusive Pädagogik", "score": 0.357208957819272, "surface": "Inklusion"}, {"type": "CONCEPT", "uri": "https://www.wikidata.org/wiki/Q1055771", "label": "Inklusive Pädagogik", "score": 0.357208957819272, "surface": "Inklusion"}, {"type": "ORGANISATION", "uri": "https://www.wikidata.org/wiki/Q1153045", "label": "Juniorenfirma", "score": 0.4303603950632502, "surface": "Schülerfirma"}, {"type": "CONCEPT", "uri": "https://www.wikidata.org/wiki/Q1334101", "label": "Elternvertretung", "score": 0.4412468220828647, "surface": "Schulpflegschaft"}, {"type": "CONCEPT", "uri": "https://www.wikidata.org/wiki/Q1334101", "label": "Elternvertretung", "score": 0.4412468220828647, "surface": "Schulpflegschaft"}, {"type": "CONCEPT", "uri": "https://www.wikidata.org/wiki/Q3331719", "label": "Quadratdezimeter", "score": 0.40216333888758043, "surface": "Quadratmeter"}, {"type": "CONCEPT", "uri": "https://www.wikidata.org/wiki/Q2616", "label": "7. Juni", "score": 0.44292018392848886, "surface": "7. Juni"}, {"type": "CONCEPT", "uri": "https://www.wikidata.org/wiki/Q331483", "label": "Abriss", "score": 0.36677284303345536, "surface": "Rückbau"}, {"type": "CONCEPT", "uri": "https://www.wikidata.org/wiki/Q331483", "label": "Abriss", "score": 0.36677284303345536, "surface": "Rückbau"}, {"type": "CONCEPT", "uri": "https://www.wikidata.org/wiki/Q331483", "label": "Abriss", "score": 0.36677284303345536, "surface": "Rückbau"}, {"type": "CONCEPT", "uri": "https://www.wikidata.org/wiki/Q646754", "label": "offener Brief", "score": 1, "surface": "offene Brief"}, {"type": "CONCEPT", "uri": "https://www.wikidata.org/wiki/Q138422", "label": "Pflegschaft", "score": 0.4484788039805682, "surface": "Pflegschaft"}, {"type": "CONCEPT", "uri": "https://www.wikidata.org/wiki/Q1207346", "label": "Dezernat", "score": 0.4340148401851611, "surface": "Dezernat"}, {"type": "CONCEPT", "uri": "https://www.wikidata.org/wiki/Q2251117", "label": "Schulentwicklung", "score": 0.42434014884208254, "surface": "Schulentwicklung"}, {"uri": "http://meta.xminutes.net/xmn/ent::0495af26f11da0ec2dba292ab3c7b4ad3cdd635b", "score": 0.010728605709146086, "type": "XMN-TAG", "surface": "Gebäudewirtschaft", "label": "Gebäudewirtschaft", "id": "ent::0495af26f11da0ec2dba292ab3c7b4ad3cdd635b", "source": "txtwerk"}, {"uri": "http://meta.xminutes.net/xmn/ent::8c0281e072e67101a5098b86cb66407b64f31eeb", "score": 0.010666994453411953, "type": "XMN-TAG", "surface": "Sanierung", "label": "Sanierung", "id": "ent::8c0281e072e67101a5098b86cb66407b64f31eeb", "source": "txtwerk"}, {"uri": "http://meta.xminutes.net/xmn/ent::0e21c886b5b8b829ac0b50b7728c5935d0ab84bf", "score": 0.010431448590390899, "type": "XMN-TAG", "surface": "Schule", "label": "Schule", "id": "ent::0e21c886b5b8b829ac0b50b7728c5935d0ab84bf", "source": "txtwerk"}, {"uri": "http://meta.xminutes.net/xmn/ent::7942d381717fd609fe04a6a1bbb04ed6a551f2b7", "score": 0.010264174634795675, "type": "XMN-TAG", "surface": "Eltern", "label": "Eltern", "id": "ent::7942d381717fd609fe04a6a1bbb04ed6a551f2b7", "source": "txtwerk"}]}, "shortText": "Die Eltern protestieren gegen den ersatzlosen Rückbau aus Brandschutzgründen", "title": "Räume für Inklusionsangebote sollen abgeschafft werden", "fullText": "In einem offenen Brief an Bildungsdezernentin Agnes Klein und die Betriebsleiterin der Gebäudewirtschaft, Petra Rinnenburger wendet sich die Schulpflegschaft der Lise-Meitner-Gesamtschule mit Lutz Tempel als Vorsitzendem gegen den geplanten kurzfristigen Rückbau der für Inklusionszwecke nutzbaren, separaten Räume an der Gesamtschule. Das sei nicht hinnehmbar.\n\nSchule und Eltern haben sich mit Sanierungsforderungen arrangiert\n\nIn einer Arbeitsgruppe Inklusion werde seit Jahren nach Lösungen gesucht, wie man den Förderkindern einigermaßen gerecht werden könne – auch mit Räumen für besondere Angebote. 2014 sei mit der Gebäudewirtschaft beschlossen worden, die Räume der sogenannten kleinen Mensa als Inklusionsräume zu nutzen. Dass dazu zusätzliche brandschutztechnische Anforderungen zu beachten waren, sei schon damals im Protokoll festgehalten worden.\n\nSeit dieser Zeit würden die Räume für Inklusion, die preisgekrönte Schülerfirma ökotec und Angebote des „aak-köln e.V. – Arbeitskreis für das ausländische Kind“ zur schnelleren Integration genutzt. Die Schulpflegschaft erläutert einen langen, schwierigen Weg, den die Stadt zur Sanierung der Räumlichkeiten seit 2015 vorgegeben und immer wieder verändert habe. Schule und Eltern hätten sich damit arrangiert – auch aus wirtschaftlichen Gründen, da Container oder ein Neubau für die Stadt nicht finanzierbar seien.\n\nKosten sind auf eine Million Euro angewachsen\n\nAls die Sanierung 2016 nicht wie versprochen erfolgte, habe die Schulpflegschaft den Sachstand erfragt und erfahren, die Instandsetzungskosten seien auf eine Viertelmillion Euro gestiegen. Im März 2017 seien die Kosten plötzlich wegen Erfordernissen des Brandschutzes auf rund eine Million Euro angewachsen.\n\nPro Quadratmeter seien das 11.000 Euro Kosten – schwer nachvollziehbar, finden die Eltern. Im Mai habe es dann geheißen, die Räume dürften gar nicht mehr genutzt und müssten geräumt werden. Am 7. Juni solle der Rückbau erfolgen. Eine Alternative gebe es nicht.\n\nAlles zuvor Gesagte zähle plötzlich nicht mehr\n\nEs sei unakzeptabel, dass plötzlich „alles zuvor Gesagte nicht mehr zählt und die LMG statt der versprochenen mehr Räume durch den Rückbau weniger besitzt, und dies aus Brandschutzgründen“, schreibt der Pflegschaftsvorstand.\n\nDies werde nicht mehr hingenommen. Die Eltern erwarten innerhalb von zwei Wochen ein Konzept. Bis dahin müsse der Rückbau ausgesetzt werden. Falls der offene Brief zu keiner Darstellung führe, wie es weitergehen soll, behalte sich die Pflegschaft vor, die Rückbaumaßnahmen zu behindern.\n\nDas Dezernat für Bildung, Jugend und Sport teilte auf Anfrage mit, beim Amt für Schulentwicklung seien Recherchen eingeleitet worden. Sie waren bei Redaktionsschluss noch nicht beendet.", "thumbnail": {"credits": "Bild: dpa", "medium": "http://www.ksta.de/image/27756424/4x3/1024/768/c19496766d8a662051d49030aa1ec858/qE/inklusion.jpg", "large": "http://www.ksta.de/image/27756424/4x3/1024/768/c19496766d8a662051d49030aa1ec858/qE/inklusion.jpg", "small": "http://www.ksta.de/image/27756424/4x3/1024/768/c19496766d8a662051d49030aa1ec858/qE/inklusion.jpg"}}, "type": "newsitem", "process": {"todo": [], "done": ["import.rss", "process.item.clean", "process.metadata.txtwerk", "process.metadata.dandelion", "process.metadata.refinery", "process.metadata.location", "process.item.bouncer", "process.datamover"]}, "feed": "rss-ksta", "sourceID": "http://www.ksta.de/27754438", "instance": "production-default", "sourceUrl": "http://www.ksta.de/koeln/porz/gesamtschule-in-porz-raeume-fuer-inklusionsangebote-sollen-abgeschafft-werden-27754438", "protocol": [{"in": 1497106692453, "instance": "production-default", "out": 1497106692656, "service": "import.rss"}, {"in": 1497106693009, "instance": "dev", "out": 1497106693039, "service": "process.item.clean"}, {"in": 1497106693280, "instance": "production-default", "out": 1497106693933, "service": "process.metadata.txtwerk"}, {"in": 1497106694160, "instance": "production-default", "out": 1497106697506, "service": "process.metadata.dandelion"}, {"in": 1497106697610, "instance": "production-default", "out": 1497106697660, "service": "process.metadata.refinery"}, {"in": 1497106697760, "instance": "production-default", "out": 1497106697761, "service": "process.metadata.location"}, {"in": 1497106697985, "instance": "dev", "out": 1497106697985, "service": "process.item.bouncer"}, {"in": 1497106698158, "instance": "production-default", "out": 1497106698208, "service": "process.datamover"}], "source": "ksta.de", "_rev": "1-c9df73160be05306794ffe2c7af67a88", "rejected": [], "importer": "import.rss", "publishDate": "2017-06-10T14:58:18+00:00", "contentType": "text"}